girder_client_mount/__init__.py
girder_client_mount/girder_client_mount.py
tests/__init__.py
tests/test_mount.py
girder_client_mount-0.3.4.dist-info/LICENSE
girder_client_mount-0.3.4.dist-info/METADATA
girder_client_mount-0.3.4.dist-info/WHEEL
girder_client_mount-0.3.4.dist-info/entry_points.txt
girder_client_mount-0.3.4.dist-info/top_level.txt
girder_client_mount-0.3.4.dist-info/RECORD
