Metadata-Version: 2.1
Name: girder_client_mount
Version: 0.3.4
Summary: Mount a girder server via fuse
Home-page: https://github.com/DigitalSlideArchive/girder-client-mount
Author: Kitware, Inc.
Author-email: kitware@kitware.com
License: Apache Software License 2.0
Keywords: girder,fuse,girder-client
Classifier: Development Status :: 4 - Beta
Classifier: License :: OSI Approved :: Apache Software License
Classifier: Natural Language :: English
Classifier: Programming Language :: Python :: 3
Classifier: Programming Language :: Python :: 3.8
Classifier: Programming Language :: Python :: 3.9
Classifier: Programming Language :: Python :: 3.10
Classifier: Programming Language :: Python :: 3.11
Classifier: Programming Language :: Python :: 3.12
Classifier: Programming Language :: Python :: 3.13
Requires-Python: >=3.8
License-File: LICENSE
Requires-Dist: cachetools
Requires-Dist: diskcache
Requires-Dist: fusepy
Requires-Dist: girder-client
Requires-Dist: httpio
Requires-Dist: python-dateutil
